mdcoderunner/__init__.py
mdcoderunner/__main__.py
mdcoderunner/api.py
mdcoderunner/config.py
mdcoderunner/imports.py
mdcoderunner/parser.py
mdcoderunner/runner.py
mdcoderunner/temp.py
mdcoderunner/utils.py
mdcoderunner/writer.py
mdcoderunner-1.0.0.dist-info/LICENSE
mdcoderunner-1.0.0.dist-info/METADATA
mdcoderunner-1.0.0.dist-info/WHEEL
mdcoderunner-1.0.0.dist-info/entry_points.txt
mdcoderunner-1.0.0.dist-info/top_level.txt
mdcoderunner-1.0.0.dist-info/RECORD
