Metadata-Version: 2.1
Name: mdcoderunner
Version: 1.0.0
Summary: A tool for running code blocks in Markdown files.
Home-page: https://github.com/SivaSankarS365/Markdown-code-runner
Author: Siva Sankar Sajeev
Author-email: sivasankars365@gmail.com
License: MIT
Classifier: Development Status :: 5 - Production/Stable
Classifier: Intended Audience :: Developers
Classifier: License :: OSI Approved :: MIT License
Classifier: Programming Language :: Python :: 3
Classifier: Programming Language :: Python :: 3.6
Classifier: Programming Language :: Python :: 3.7
Classifier: Programming Language :: Python :: 3.8
Classifier: Programming Language :: Python :: 3.9
License-File: LICENSE
Requires-Dist: jinja2 (==3.1.3)
